knead/__init__.py
knead/__main__.py
knead/conversions/__init__.py
knead/conversions/json_to_pb.py
knead/conversions/pb_to_npy.py
knead/conversions/ttf_to_ttx.py
knead/conversions/ttx_to_json.py
knead/utils/__init__.py
knead/utils/glyph_batch_pb2.py
knead/utils/utils.py
knead-0.2.0.dist-info/LICENSE
knead-0.2.0.dist-info/METADATA
knead-0.2.0.dist-info/WHEEL
knead-0.2.0.dist-info/entry_points.txt
knead-0.2.0.dist-info/top_level.txt
knead-0.2.0.dist-info/RECORD
