Metadata-Version: 2.1
Name: knead
Version: 0.2.0
Summary: A command line tool for preprocessing, manipulating and serializing font files for deep learning applications.
Home-page: https://github.com/font-bakers/knead
Maintainer: The Font Bakers
License: MIT
Project-URL: Documentation, https://font-bakers.github.io/knead/
Project-URL: Issue Tracker, https://github.com/font-bakers/knead/issues
Platform: UNKNOWN
Classifier: Development Status :: 3 - Alpha
Classifier: Environment :: Console
Classifier: License :: OSI Approved :: MIT License
Classifier: Natural Language :: English
Classifier: Operating System :: OS Independent
Classifier: Programming Language :: Python
Classifier: Programming Language :: Python :: 3
Classifier: Programming Language :: Python :: 3.5
Classifier: Topic :: Scientific/Engineering
Classifier: Topic :: Text Processing :: Fonts
Requires-Python: >=3.5.2
Requires-Dist: absl-py
Requires-Dist: fonttools (==3.43.0)
Requires-Dist: numpy
Requires-Dist: protobuf
Requires-Dist: tqdm
